egnar/__init__.py
egnar-0.2.dist-info/LICENSE.txt
egnar-0.2.dist-info/METADATA
egnar-0.2.dist-info/WHEEL
egnar-0.2.dist-info/top_level.txt
egnar-0.2.dist-info/RECORD
